{
    "ISI": [
        {
            "model": "FluBcast",
            "changes": [
                "model-output/ISI-FluBcast/2025-05-07-ISI-FluBcast.csv"
            ]
        },
        {
            "model": "RC_AdaptEns2",
            "changes": [
                "model-output/ISI-RC_AdaptEns2/2025-05-07-ISI-RC_AdaptEns2.csv"
            ]
        }
    ],
    "ECDC": [
        {
            "model": "SARIMA",
            "changes": [
                "model-output/ECDC-SARIMA/2025-05-07-ECDC-SARIMA.csv"
            ]
        },
        {
            "model": "soca_simplex",
            "changes": [
                "model-output/ECDC-soca_simplex/2025-05-07-ECDC-soca_simplex.csv"
            ]
        }
    ]
}