{
    "fjordhest": [
        {
            "model": "ensemble",
            "changes": [
                "model-output/fjordhest-ensemble/2025-04-02-fjordhest-ensemble.csv"
            ]
        }
    ],
    "ISI": [
        {
            "model": "FluABCaster",
            "changes": [
                "model-output/ISI-FluABCaster/2025-04-02-ISI-FluABCaster.csv"
            ]
        },
        {
            "model": "SEIR_BRW",
            "changes": [
                "model-output/ISI-SEIR_BRW/2025-04-02-ISI-SEIR_BRW.csv"
            ]
        }
    ],
    "ItaLuxColab": [
        {
            "model": "EpiEKF",
            "changes": [
                "model-output/ItaLuxColab-EpiEKF/2025-04-02-ItaLuxColab-EpiEKF.csv"
            ]
        },
        {
            "model": "EpiNetEKF",
            "changes": [
                "model-output/ItaLuxColab-EpiNetEKF/2025-04-02-ItaLuxColab-EpiNetEKF.csv"
            ]
        }
    ],
    "QMUL": [
        {
            "model": "ARIMA",
            "changes": [
                "model-output/QMUL-ARIMA/2025-04-02-QMUL-ARIMA.csv"
            ]
        },
        {
            "model": "SEIR",
            "changes": [
                "model-output/QMUL-SEIR/2025-04-02-QMUL-SEIR.csv"
            ]
        },
        {
            "model": "SEIR_agumented",
            "changes": [
                "model-output/QMUL-SEIR_agumented/2025-04-02-QMUL-SEIR_agumented.csv"
            ]
        }
    ],
    "RIVM": [
        {
            "model": "KFdlm",
            "changes": [
                "model-output/RIVM-KFdlm/2025-04-02-RIVM-KFdlm.csv"
            ]
        }
    ],
    "ECDC": [
        {
            "model": "SARIMA",
            "changes": [
                "model-output/ECDC-SARIMA/2025-04-02-ECDC-SARIMA.csv"
            ]
        },
        {
            "model": "soca_simplex",
            "changes": [
                "model-output/ECDC-soca_simplex/2025-04-02-ECDC-soca_simplex.csv"
            ]
        }
    ]
}